semimutable/__init__.py
semimutable/py.typed
semimutable-0.1.0.dist-info/METADATA
semimutable-0.1.0.dist-info/WHEEL
semimutable-0.1.0.dist-info/licenses/LICENSE
semimutable-0.1.0.dist-info/RECORD
