Metadata-Version: 2.4
Name: semimutable
Version: 0.1.0
Summary: Drop-in replacement for Python's built-in `dataclasses` module, allowing for certain fields to be mutable while others remain immutable.
Project-URL: Homepage, https://github.com/Glinte/semimutable
Project-URL: Repository, https://github.com/Glinte/semimutable
Project-URL: Issues, https://github.com/Glinte/semimutable/issues
Author: Glinte
License-Expression: MIT
License-File: LICENSE
Keywords: dataclasses
Classifier: Development Status :: 3 - Alpha
Classifier: Intended Audience :: Developers
Classifier: License :: OSI Approved :: MIT License
Classifier: Programming Language :: Python :: 3 :: Only
Classifier: Programming Language :: Python :: 3.12
Classifier: Programming Language :: Python :: 3.13
Classifier: Programming Language :: Python :: 3.14
Classifier: Programming Language :: Python :: Implementation :: CPython
Classifier: Topic :: Software Development :: Libraries
Requires-Python: >=3.12
